<?xml version="1.0" encoding="UTF-8" standalone="yes"?>

<addons>
	
	
<addon id="plugin.video.laplaza" version="1.0.15b" name="[COLOR orange][B]Laplaza[/B][/COLOR]" provider-name="Cy4Root">
	<requires>
		<import addon="xbmc.python" version="2.19.0" />
		<import addon="script.laplaza.metadata" version="1.0.0" />
		<import addon="script.module.liptonscrapers" />
		<import addon="script.module.resolveurl" />
		<import addon="script.module.requests" />
		<import addon="script.module.metahandler" version="1.0.0" />
		<import addon="script.module.openscrapers" optional="true" />
        <import addon="plugin.video.youtube"/>
	</requires>
	<extension point="xbmc.python.pluginsource" library="default.py">
		<provides>video</provides>
        <provides>audio</provides>
	</extension>
        <extension library="service.py" point="xbmc.service" start="[startup|login]" />
	<extension point="xbmc.addon.metadata">
                <summary lang="en">[COLORblue]Placenta.Fork[/COLOR]</summary>
		<description lang="en">[I][B]Laplaza Movies and TV (optional) Multi sources options, default not installed[/B][/I][CR][CR]This addon does not form part of the Kodi Media Centre. Please do not seek assistance with this addon from any of the Official Kodi Support Channels.[CR][CR]The author does not host any of the content in this addon and takes no responsibility for content found.</description>
		<platform>all</platform>
		<license>GNU GENERAL PUBLIC LICENSE. Version 3, 29 June 2007</license>
		<disclaimer lang="en">The author of this addon do not host any of the content which is found and have no affiliation with any of the content providers. This addon simply searches websites for content. Use at your own risk!</disclaimer>
		<assets>
			<icon>icon.png</icon>
			<fanart>fanart.jpg</fanart>
		</assets>
		<news>
			Orginal copy Placenta
		</news>
	</extension>
</addon>
	
<addon id="script.laplaza.artwork" version="1.0.02" name="Laplaza Artwork" provider-name="Cy4Root">
	<requires>
		<import addon="xbmc.python" version="2.19.0"/>
	</requires>
	<extension point="xbmc.python.module" library="lib" />
	<extension point="xbmc.addon.metadata">
		<summary>Themes for the Laplaza Addon</summary>
		<description>Artwork Module for the Laplaza Addon</description>
        <disclaimer lang="en">The author is not responsible for the use of this addon. The author is not responsible for the content found using this addon. The author does not host or own any content found within this addon.
The author is in no way affiliated with Kodi, Team Kodi, or the XBMC Foundation.
This is a Non-profit resource, organized solely for educational purposes which is protected under the Fair-Use doctrine of the Copyright Act, Specifically section 107, which does promote freedom of expression, by permitting the unlicensed use of copyright-protected works.</disclaimer>
        <license>GNU</license>
		<platform>all</platform>
	</extension>
</addon>
	
<addon id="script.laplaza.metadata" version="1.0.02" name="Laplaza Metadata" provider-name="Cy4Root">
	<requires>
		<import addon="xbmc.python" version="2.19.0"/>
	</requires>
	<extension point="xbmc.python.module" library="lib" />
	<extension point="xbmc.addon.metadata">
		<summary>Metadata for the Laplaza Addon</summary>
		<description>Metadata for Laplaza</description>
        <disclaimer lang="en">The author is not responsible for the use of this addon. The author is not responsible for the content found using this addon. The author does not host or own any content found within this addon.
The author is in no way affiliated with Kodi, Team Kodi, or the XBMC Foundation.
This is a Non-profit resource, organized solely for educational purposes which is protected under the Fair-Use doctrine of the Copyright Act, Specifically section 107, which does promote freedom of expression, by permitting the unlicensed use of copyright-protected works.</disclaimer>
        <license>GNU</license>
		<platform>all</platform>
	</extension>
</addon>
		
<addon id="plugin.video.covenant" version="1.1.32" name="Covenant" provider-name="Covenant">
	<requires>
		<import addon="xbmc.python" version="2.19.0" />
		<import addon="script.module.requests" version="2.19.1" />
		<import addon="script.module.beautifulsoup4" version="4.5.3"/>
		<import addon="script.module.metahandler" version="2.9.0" />
		<import addon="plugin.video.youtube" version="6.2.0"/>
		<import addon="script.module.resolveurl" version="5.0.27"/>
		<import addon="script.module.openscrapers" />
		<import addon="script.module.addon.signals" version="0.0.3"/>
		<import addon="script.module.resolveurl" />
		<import addon="script.module.covenant" />
		<import addon="script.covenant.artwork" version="1.0.0" />
		<import addon="script.covenant.metadata" version="1.0.0" />
	</requires>
	<extension point="xbmc.python.pluginsource" library="covenant.py">
		<provides>video</provides>
	</extension>
	<extension point="xbmc.service" library="service.py" start="startup" />
	<extension point="xbmc.addon.metadata">
		<summary lang="en">Covenant</summary>
		<description lang="en">[I]A New Generation[/I][CR][CR][B]Covenant Movies and TV[/B][CR][CR]This addon does not form part of the Kodi Media Centre. Please do not seek assistance with this addon from any of the Official Kodi Support Channels.[CR][CR]The author does not host any of the content in this addon and takes no responsibility for content found.</description>
		<description lang="hr">[I]Nova generacija[/I][CR][CR][B]Covenant Filmova i TV serija[/B][CR][CR]Ovaj dodatak ne sadrži dijelove Kodi Medijskog Centra. Ne tažite pomoć za ovaj dodatak na službenim kanalima podrške za Kodi.[CR][CR]Autor ne posjeduje bilo kakav sadržaj u ovom dodatku i ne preuzima bilo kakvu odgovornost za pronađeni sadržaj.</description>
		<description lang="he">[I]הדור החדש[/I][CR][CR][B]Covenant סרטים וסדרות[/B][CR][CR]ההרחבה הזו אינה חלק של Kodi Media Center. אנא אל תבקש עזרה עם ההרחבה זה מכל אחד מערוצי התמיכה הרשמיים של Kodi [CR][CR]. אין למחבר תוכן בהרחבה הזו והמחבר אינו אחראי לתוכן שנמצא.</description>
		<platform>all</platform>
		<license>GNU GENERAL PUBLIC LICENSE. Version 3, 29 June 2007</license>
		<forum></forum>
		<website></website>
		<source></source>
		<disclaimer lang="en">The author of this addon do not host any of the content which is found and have no affiliation with any of the content providers. This addon simply searches websites for content. Use at your own risk!</disclaimer>
		<disclaimer lang="hr">Autor ovog dodatka ne posjeduje bilo kakav sadržaj koji je pronađen i nije povezan sa bilo kojim izvorom sadržaja. Ovaj dodatak samo pretražuje sadržaj na web stranicama. Koristite ga na vlastitu odgovornost!</disclaimer>
		<disclaimer lang="he">מחבר ההרחבה זה אינו מארח את התוכן שיתכן ויימצא ואין לו זיקה לאף אחד מספקי התוכן. הרחבה רק מחפשת תוכן שקיים באתרי אינטרנט. השימוש בהרחבה הוא על אחריותך בלבד!</disclaimer>
		<assets>
			<icon>icon.png</icon>
			<fanart>fanart.jpg</fanart>
    			<screenshot>resources/screenshots/screenshot-01.jpg</screenshot>
    			<screenshot>resources/screenshots/screenshot-02.jpg</screenshot>
    			<screenshot>resources/screenshots/screenshot-03.jpg</screenshot>
		</assets>
		<news></news>
	</extension>
</addon>
	
<addon id="script.covenant.artwork" version="1.0.3" name="Covenant Artwork" provider-name="Covenant">
	<requires>
		<import addon="xbmc.python" version="2.19.0"/>
	</requires>
	<extension point="xbmc.python.module" library="lib" />
	<extension point="xbmc.addon.metadata">
		<summary>Themes for the Covenant Addon</summary>
		<description></description>
		<platform>all</platform>
	</extension>
</addon>
	
<addon id="script.covenant.metadata" version="1.0.2" name="Covenant Metadata" provider-name="Covenant">
	<requires>
		<import addon="xbmc.python" version="2.19.0"/>
	</requires>
	<extension point="xbmc.python.module" library="lib" />
	<extension point="xbmc.addon.metadata">
		<summary>Metadata for the Covenant Addon</summary>
		<description>Metadata for Covenant are maintained separately to make distribution of the the addon itself easier/faster.</description>
		<platform>all</platform>
	</extension>
</addon>
	
<addon id="script.module.covenant" name="Covenant Module" version="1.00.027" provider-name="Covenant">
	<requires>
		<import addon="xbmc.python" version="2.1.0" />
	</requires>
	<extension point="xbmc.python.module" library="lib" />
	<extension point="xbmc.addon.metadata">
		<platform>all</platform>
		<summary lang="en">Covenant</summary>
	</extension>
</addon>
	

	

<addon id="plugin.video.chucky" name="[COLOR red][B]Chucky[COLOR gold] Video[/B][/COLOR]" provider-name="Cy4Root" version="1.2.0.7b">
    <requires>
        <import addon="xbmc.python" version="2.19.0" />
        <import addon="script.module.liptonscrapers" />
        <import addon="script.module.resolveurl" />
        <import addon="script.module.metahandler" />
        <import addon="script.module.requests" />
    </requires>
    <extension library="main.py" point="xbmc.python.pluginsource">
        <provides>video</provides>
    </extension>
    <extension library="service.py" point="xbmc.service" start="[startup|login]" />
    <extension point="xbmc.addon.metadata">
        <summary lang="en">Movies and TvShows</summary>
        <description lang="en">Based on 13Clowns and Exodus # Liptonscrapers or build providers choice # GNU license</description>
        <disclaimer lang="en">The author is not responsible for the use of this addon. The author is not responsible for the content found using this addon. The author does not host or own any content found within this addon.[CR]The author is in no way affiliated with Kodi, Team Kodi, or the XBMC Foundation. </disclaimer>
        <license>GNU</license>
        <platform>all</platform>
        <assets>
            <icon>icon.gif</icon>
            <fanart>fanart.gif</fanart>
            <screenshot>resources/screenshots/screenshot_1.png</screenshot>
        </assets>
        <news> </news>
    </extension>
</addon>

<addon id="plugin.video.mirrorv2" name="[COLOR orange][B]MirRoR V2[COLOR white] Video[/B][/COLOR]" provider-name="Cy4Root" version="2.0.12">
	<requires>
		<import addon="xbmc.python" version="2.19.0" />
		<import addon="script.module.openscrapers" />
		<import addon="script.module.resolveurl" />
		<import addon="script.module.requests" />
		<import addon="script.module.metahandler" />
        	<import addon="plugin.video.youtube"/>
	</requires>
    <extension library="main.py" point="xbmc.python.pluginsource">
        <provides>video</provides>
    </extension>
    <extension library="service.py" point="xbmc.service" start="[startup|login]" />
    <extension point="xbmc.addon.metadata">
        <summary lang="en">Movies and TV Shows</summary>
        <description lang="en">[B]MirrorV2[/B][CR] [B]***OpenScrapers Edition***[/B][CR][CR]This addon does not form part of the Kodi Media Centre. Please do not seek assistance with this addon from any of the Official Kodi Support Channels.[CR][CR]The author does not host any of the content in this addon and takes no responsibility for content found.</description>
        <disclaimer lang="en">The author is not responsible for the content found using this addon. The author does not host or own any content found within this addon.[CR]The author is in no way affiliated with Kodi, Team Kodi, or the XBMC Foundation. </disclaimer>
        <license>GNU</license>
        <platform>all</platform>
        <assets>
            <icon>icon.gif</icon>
            <fanart>fanart.gif</fanart>
            <screenshot>resources/screenshots/screenshot01a.png</screenshot>
	    <screenshot>resources/screenshots/screenshot02a.png</screenshot>
	    <screenshot>resources/screenshots/screenshot03a.png</screenshot>
        </assets>
        <news>v2.0.11 Openscrapers Edition</news>
    </extension>
</addon>
	
		
<addon id="script.module.urlresolver" name="URLResolver" version="5.0.43" provider-name="tvaddons">
    <requires>
        <import addon="xbmc.python" version="2.1.0" />
        <import addon="plugin.video.youtube" optional="true" />
        <import addon="script.module.python.twitch" optional="true" />
        <import addon="script.module.cryptopy" version="1.2.6" optional="true" />
        <import addon="plugin.video.gdrive" optional="true" />
    </requires>
    <extension point="xbmc.python.module" library="lib" />
    <extension point="xbmc.python.pluginsource" library="lib/default.py" />
    <extension point="xbmc.addon.metadata">
        <platform>all</platform>
        <summary lang="en">Resolve common video host URL's to be playable in XBMC/Kodi.</summary>
        <summary lang="es">Resolver enlaces a videos de sitios populares para poder reproducirlos en XBMC/Kodi.</summary>
        <summary lang="hr">Prilagodi najčešće URL-ove video izvora kako bi radili u XBMC/Kodiju.</summary>
        <summary lang="el">Επίλυση συνδέσμων κοινών εξυπηρετητών σε μορφή βίντεο ικανό για αναπαραγωγή στο XBMC/Kodi.</summary>
        <description lang="en">Resolve common video host URL's to be playable in XBMC/Kodi, simplify addon development of video plugins requiring multi video hosts.</description>
        <description lang="hr">Prilagodi najčešće URL-ove video izvora kako bi radili u XBMC/Kodiju, pojednostavnjuje razvoj priključaka za video dodatke koji zahtjevaju višestruke video izvore.</description>
        <forum>https://www.tvaddons.co/forums</forum>
        <website>https://www.tvaddons.co</website>
    </extension>
</addon>


<addon id="plugin.video.PLsportowo" name="Sportowa TV" version="1.8.9" provider-name="mbebe">
	<requires>
		<import addon="xbmc.python" version="2.25.0"/>
		<import addon="script.module.requests" />
		<import addon="script.module.parsedom" version="2.5.2"/>
		<import addon="script.module.inputstreamhelper" version="0.3.3"/>
		<import addon="script.module.resolveurl" version="5.0.00"/>
        <import addon="script.module.streamlink.base" />
	</requires>
	<extension point="xbmc.python.pluginsource" library="maintv.py">
		<provides>video</provides>
	</extension>
	<extension point="xbmc.addon.metadata">
		<description>Wydarzenia sportowe</description>
		<disclaimer>https://github.com/mbebe/blomqvist</disclaimer>
		<summary>Relacje Live</summary>
		<language></language>
		<platform>all</platform>
		<license>GNU GENERAL PUBLIC LICENSE. Version 2, June 1991</license>
		<website></website>
		<assets>
			<icon>icon.png</icon>
			<fanart>fanart.jpg</fanart>
		</assets>
	</extension>
</addon>

<?xml version="1.0" encoding="UTF-8" standalone="yes"?>
<addon id="plugin.video.openmeta" name="OpenMeta" version="1.4.14" provider-name="A4K">
	<requires>
		<import addon="xbmc.python" version="2.25.0"/>
		<import addon="metadata.tvdb.com" version="3.0.14"/>
		<import addon="script.module.futures" version="2.2.0"/>
		<import addon="script.module.requests" version="2.19.1"/>
		<import addon="script.module.requests-cache" version="0.4.13"/>
	</requires>
	<extension point="xbmc.python.pluginsource" library="addon.py">
		<provides>video</provides>
	</extension>
	<extension point="xbmc.service" library="service.py"/>
	<extension point="kodi.context.item">
		<menu id="kodi.core.main">
			<item library="context.py">
				<label>OpenMeta - Default Player</label>
				<visible>!String.StartsWith(ListItem.path,plugin://plugin.video.openmeta/)+[String.IsEqual(ListItem.dbtype,episode)|String.IsEqual(ListItem.dbtype,movie)]</visible>
			</item>
			<item library="context2.py">
				<label>OpenMeta - Choose Player</label>
				<visible>String.IsEqual(ListItem.dbtype,movie) | String.IsEqual(ListItem.dbtype,episode)</visible>
			</item>
		</menu>
	</extension>
	<extension point="xbmc.addon.metadata">
		<platform>all</platform>
		<summary lang="en">TMDb, TVDb and Trakt browser</summary>
		<description lang="en">Browse The MovieDb, The TVDb, Trakt and pass info along to library or an addon. Needs player-files and the appropriate addon to play the files.</description>
		<assets>
			<icon>resources/icon.png</icon>
			<fanart>resources/fanart.jpg</fanart>
			<screenshot>resources/screenshot000.jpg</screenshot>
			<screenshot>resources/screenshot001.jpg</screenshot>
			<screenshot>resources/screenshot002.jpg</screenshot>
		</assets>
		<license></license>
		<forum></forum>
		<website></website>
		<source></source>
		<news>
		1.4.14 - Fix bug with missing ID in TV menus
		1.4.13 - Added realtitle (movies) and realname (tvshows) parameters for plexkodiconnect compatibility
		1.4.12 - Handle non-existent 'filename' key in TVDB data.
		1.4.11 - TVDB API fix, thanks to @ruinernin and @bg-22 (among others)!
				 BUG: Some artwork may not load for certain items, due to ongoing API instability.
		1.4.10 - Added language option for player-files (TV)
		1.4.9  - Fix art in TV menus
		1.4.8  - Fix crash from empty "first_aired" string"
		1.4.7  - Fix crash when we can't contact TVDB
		1.4.6  - Fix crashes from non-existent keys
		1.4.5  - Added default play action, options for movies are; Play/OpenInfo and options for episodes are; Play/OpenInfo(TV Show info)/OpenInfo(Episode info).
		1.4.4  - Fix clearlogo for movies
		1.4.3  - Fix typo in season fanart request.
		1.4.2  - Add fanart caching
		1.4.1  - Fix season artwork
		1.4.0  - Add unwatched counts for shows/seasons.
		1.3.2  - Fix "Upcoming Episodes" and "Next Episodes".
		1.3.1  - Fixed "Next Page" bug with widgets.</news>
	</extension>
</addon>
	
<addon id="script.extendedinfo" name="OpenInfo" version="6.2.4" provider-name="A4K">
	<requires>
		<import addon="xbmc.python" version="2.25.0"/>
		<import addon="script.module.pil" version="1.1.7"/>
		<import addon="plugin.video.youtube" version="6.2.2"/>
		<import addon="script.module.requests" version="2.9.1"/>
		<import addon="script.skin.helper.service" version="1.0.0"/>
		<import addon="resource.images.studios.white" version="0.0.18"/>
		<import addon="plugin.video.openmeta" version="1.0.0" optional="true"/>
	</requires>
	<extension point="xbmc.python.script" library="script.py"/>
	<extension point="xbmc.python.pluginsource" library="plugin.py">
		<provides>video</provides>
	</extension>
	<extension point="kodi.context.item">
		<menu id="kodi.core.main">
			<item library="context.py">
				<label>OpenInfo</label>
				<visible>String.IsEqual(ListItem.dbtype,movie) | String.IsEqual(ListItem.dbtype,tvshow) | String.IsEqual(ListItem.dbtype,season) | String.IsEqual(ListItem.dbtype,episode) | String.IsEqual(ListItem.dbtype,actor) | String.IsEqual(ListItem.dbtype,director)</visible>
			</item>
		</menu>
	</extension>
	<extension point="xbmc.addon.metadata">
		<reuselanguageinvoker>false</reuselanguageinvoker>
		<platform>all</platform>
		<summary>Fork of the ExtendedInfo script from phil65</summary>
		<description>This script offers various possibilities to display online content inside skins as well as a complete MovieDB browser including info dialogs for various media types. Needs skin implementation for lot of functions and OpenMeta for library functions.</description>
		<assets>
			<icon>resources/icon.png</icon>
			<fanart>resources/fanart.jpg</fanart>
			<screenshot>resources/screenshot1.jpg</screenshot>
			<screenshot>resources/screenshot2.jpg</screenshot>
			<screenshot>resources/screenshot3.jpg</screenshot>
		</assets>
		<news>
		6.2.4 - Specify param in TV Show ID
		6.2.3 - Fix TV Show trailers
		6.2.2 - Added ability to search using the tvdb_id for "extendedepisodeinfo"
		6.2.1 - Fix context menu now available for widgets pointing to OpenInfo's video addon items
		6.2.0 - Added context menu force "player select" to the play button, available via "c" and long press "enter" button
		</news>
	</extension>
</addon>


   
<addon id="script.ezcleanLite" name="EZ Clean Lite version" provider-name="People" version="1.1">
    <requires>
        <import addon="xbmc.python" version="2.1.0"/>
        <import addon="script.module.requests" />
    </requires>
    <extension library="default.py" point="xbmc.python.pluginsource">
        <provides>program executable</provides>
    </extension>
    <extension library="service.py" point="xbmc.service" start="startup" />
    <extension point="xbmc.addon.metadata">
        <summary lang="en">A Streamlined Utility Tool for Kodi.</summary>
        <description lang="en">A Streamlined Utility Tool for Kodi.</description>
        <language/>
        <platform>all</platform>
        <license>The MIT License</license>
        <assets>
            <icon>icon.png</icon>
            <fanart>fanart.jpg</fanart>
        </assets>
    </extension>
</addon>

<addon id="service.subloader_custom"
    name="service.subloader_custom" version="0.1.5" provider-name="Cy4Root">
  <requires>
    <import addon="xbmc.python" version="2.14.0"/>
  </requires>
  <extension point="xbmc.service" library="system.py" start="login"></extension>  
  <extension point="xbmc.addon.metadata">
    <summary lang="en">Automatic subtitles without logging in or opensubtitle addon @Cy4Root</summary>
    <description lang="en">Default Dutch subtitle</description>
    <platform>all</platform>
    <language>en</language>
    <license>GPL</license>
    <website></website>
	<assets>
		<icon>icon.jpg</icon>
		<fanart>fanart.jpg</fanart>
		<screenshot></screenshot>
		<screenshot></screenshot>
	</assets>
    <source></source>
    <forum></forum>
    <email></email>
	<news></news>
  </extension>
</addon>

	


<addon id="plugin.close.kodi" name="[COLOR red] Force Close Kodi[/COLOR] " version="3.1.3" provider-name="Based_Skid">
  <requires>
    <import addon="xbmc.python" version="2.1.0"/>
  </requires>
  <extension point="xbmc.python.pluginsource" library="default.py">
        <provides>executable</provides>
  </extension>
  <extension point="xbmc.addon.metadata">
    <summary lang="en">Force Close Kodi</summary>
    <description lang="en"></description>
    <platform>all</platform>
  </extension>
</addon>
	
	
<addon id="plugin.program.tidycleaner" 
	     name="[B][COLOR lime]Tidy Cleaner[/COLOR][/B]" 
	     version="1.0.1" 
	     provider-name="DROID REBORN">
  <requires>
  	<import addon="xbmc.python" version="2.1.0"/>
  </requires>
  <extension point="xbmc.python.pluginsource" library="default.py">
        <provides>executable</provides>
  </extension>
  <extension point="xbmc.service" library="service.py" start="startup">
  </extension> 
  <extension point="xbmc.addon.metadata">
    <platform>all</platform>
    <summary lang="en">[COLOR lime]Cleaning Tool Use Daily.!!![/COLOR]</summary>
    <description lang="en"> Cleaning Tool Use Daily. </description>
    <disclaimer lang="en"></disclaimer>
    <language></language>
    <platform>all</platform>
    <license>GNU GENERAL PUBLIC LICENSE. Version 2, June 1991</license>
    <forum></forum>
    <website></website>
    <email></email>
  </extension>
</addon>
	

		
<addon
  id="plugin.video.SportsDevil"
  version="2019.05.25"
  name="SportsDevil"
  provider-name="SportsDevil">
  <requires>
   <import addon="xbmc.python" version="2.14.0"/>
   <import addon="script.module.dateutil" />
   <import addon="script.module.simplejson" />
   <import addon="script.module.six" />
   <import addon="script.module.requests" />   
   <import addon="plugin.video.f4mTester" />
   <import addon="script.module.slproxy" />
  </requires>
  <extension 
    point="xbmc.python.pluginsource"
    library="default.py">
   <provides>video</provides>
  </extension>
  <!-- <extension point="xbmc.service" library="service/streamlink_proxy.py" /> -->
  <extension point="xbmc.addon.metadata">
    <summary lang="en">SportsDevil</summary>
    <description lang="en">[I]There can only be one.[/I][CR][CR]Unofficial Kodi Addon.</description>
    <disclaimer lang="en">There can only be one.</disclaimer>
    <license>GNU GENERAL PUBLIC LICENSE. Version 2, June 1991</license>
    <platform>all</platform>
  </extension>
</addon>
	
	
<addon id="script.speedtestnet"
       name="ARNU Box Speed Tester"
       version="1.0.0"
       provider-name="ARNU Box / Josh.5">
  <requires>
    <import addon="xbmc.python" version="2.1.0"/>
  </requires>
  <extension point="xbmc.python.script"
             library="default.py">
        <provides>executable</provides>
  </extension>
  <extension point="xbmc.addon.metadata">
    <summary lang="en">ARNU Box Speed Tester</summary>
    <description lang="en">ARNU Box Speed Tester powered by speedtest.net will give you accurate Internet speed/ping test results. \n Brought to you by http://www.arnubox.com</description>
    <platform>all</platform>
  </extension>
</addon>
	

	
<addon id="script.module.laola1tv" name="Laola1 SportsTv" version="1.1" provider-name="laola1.tv">
	<requires>
		<import addon="xbmc.python" version="2.14.0"/>
		<import addon="script.module.beautifulsoup4" version="4.3.2"/>
	</requires>
	<extension point="xbmc.python.pluginsource" library="default.py">
		<provides>all</provides>
	</extension>
	<extension point="xbmc.addon.metadata">
		<platform>all</platform>
		<summary lang="en"></summary>
		<description lang="en">Provides streams from laola1.tv</description>
		<license>GNU General Public License, v2</license>
	</extension>
</addon>
	

	
<addon id="script.module.metahandler" 
     name="metahandler" 
     version="3.99.02" 
     provider-name="Eldorado">
  <requires>
    <import addon="xbmc.python" version="2.1.0" />
    <import addon="script.module.simplejson" version="3.3.0"/>
    <import addon="script.module.addon.common" version="2.0.0"/>
    <import addon="script.module.myconnpy" version="1.1.6"/>
  </requires>
  <extension point="xbmc.python.module" library="lib" />
  <extension point="xbmc.python.pluginsource" library="lib/default.py" />
  <extension point="xbmc.addon.metadata">
      <platform>all</platform>
      <summary lang="en">Downloads Artwork for TV shows, Movies and Music videos for addons and stores them in a local SQLITE database</summary>
      <description lang="en">Queries, stores, and returns metadata for TV shows, Movies and Musicvideos. [CR]Sources:[CR]www.thetvdb.com[CR]www.themoviedb.org[CR]www.imdb.com[CR]www.omdbapi.com[CR]This product uses the TMDb API but is not endorsed or certified by TMDb.</description>
      <disclaimer lang="en"></disclaimer>
      <language></language>
      <license>GNU GENERAL PUBLIC LICENSE. Version 2, June 1991</license>
      <forum></forum>
      <website></website>
      <email></email>
      <source></source>
  </extension>
</addon>


	
<addon id="script.module.resolveurl" name="ResolveURL" version="5.0.36" provider-name="jsergio">
    <requires>
        <import addon="xbmc.python" version="2.1.0" />
        <import addon="plugin.video.youtube" optional="true" />
        <import addon="script.module.python.twitch" optional="true" />
        <import addon="script.module.cryptopy" version="1.2.6" optional="true" />
        <import addon="plugin.video.gdrive" optional="true" />
    </requires>
    <extension point="xbmc.python.module" library="lib" />
    <extension point="xbmc.python.pluginsource" library="lib/default.py" />
    <extension point="xbmc.addon.metadata">
        <platform>all</platform>
        <summary lang="en">Resolve common video host URL's to be playable in XBMC/Kodi.</summary>
        <summary lang="es">Resolver enlaces a videos de sitios populares para poder reproducirlos en XBMC/Kodi.</summary>
        <summary lang="hr">Prilagodi najčešće URL-ove video izvora kako bi radili u XBMC/Kodiju.</summary>
        <summary lang="el">Επίλυση συνδέσμων κοινών εξυπηρετητών σε μορφή βίντεο ικανό για αναπαραγωγή στο XBMC/Kodi.</summary>
        <description lang="en">Resolve common video host URL's to be playable in XBMC/Kodi, simplify addon development of video plugins requiring multi video hosts.</description>
        <description lang="hr">Prilagodi najčešće URL-ove video izvora kako bi radili u XBMC/Kodiju, pojednostavnjuje razvoj priključaka za video dodatke koji zahtjevaju višestruke video izvore.</description>
    </extension>
</addon>
	

<addon id="script.module.tt" name=" TvTap" version="1.4.b" provider-name="RACC">
  <requires>
    <import addon="xbmc.python" version="2.1.0"/>
    <import addon="script.module.livestreamer" />
    <import addon="script.module.requests" />
    <import addon="script.module.routing" />
  </requires>
  <extension point="xbmc.python.pluginsource" library="addon.py">
    <provides>video</provides>
  </extension>
  <extension point="xbmc.addon.metadata">
    <description lang="en">Tap Tv Android Apk</description>
    <platform>all</platform>
  </extension>
</addon>
	

	

	
<addon id="service.subloader"
    name="SubLoader" version="0.1.4" provider-name="DenimNani">
  <requires>
    <import addon="xbmc.python" version="2.14.0"/>
  </requires>
  <extension point="xbmc.service" library="monitor.py" start="login"></extension>  
  <extension point="xbmc.addon.metadata">
    <summary lang="en">Automatic subtitles for your content</summary>
    <description lang="en">Auto download the best subtitle automatically as soon you start the video.
Special thanks to OpenSubtitles.org for providing a unique UA for Subloader.</description>
    <platform>all</platform>
    <language>en</language>
    <license>GPL</license>
    <website>https://github.com/denimnani</website>
	<assets>
		<icon>iconsubloader.png</icon>
		<fanart>fanartsubloader.png</fanart>
		<screenshot>resources/media/screenshots/screenshot1subLoader.jpg</screenshot>
		<screenshot>fanartsubloader.png</screenshot>
	</assets>
    <source>https://github.com/denimnani/service.subloader</source>
    <forum></forum>
    <email></email>
	<news>0.1.4     23.07.2019
Added Dutch language (Special thanks to Tinuz97).
Clean up project files.

0.1.3     21.07.2019
Added OS user login.
Fixed debug option.
Added more debug information.
Massive code rewrite.
Several optimizations.
Added audio language exclusions.
Added video addon exclusions.
Improved sorting settings.
Improved settings layout.
Added Do nothing option.

0.1.2     17.06.2019
Added a unique User Agent from Opensubtitles.org.

0.1.1     12.06.2019
Fixed release detection bug.
Fixed typo.

0.1.0     10.06.2019
Fixed instalation bug.
Fixed notifications bug.
Started Beta convergence.
Added default behavior selection.
Added auto donwload any subtitle if no match found.
Updated settings xml.
Updated strings po.
Release type detection improved.</news>
  </extension>
</addon>
	
<addon id="service.subtitles.opensubtitles" name="OpenSubtitles.org by OpenSubtitles" version="5.2.16a"  provider-name="Cy4Root, opensubtitles">
  <requires>
    <import addon="xbmc.python" version="2.1.0"/>
  </requires>
  <extension point="xbmc.subtitle.module"
             library="service.py" />
  <extension point="xbmc.addon.metadata">
    <summary>OpenSubtitles by Cy4Root</summary>
    <description lang="en">Anonymous search opensubtitles by Cy4Root</description>                                           
	<news>
	</news>
    <platform>all</platform>
	<language></language>
    <license>GNU GENERAL PUBLIC LICENSE V3</license>
    <forum></forum>
    <website>http://www.opensubtitles.org</website>
    <email></email>                                               
	<assets>
	    <icon>icon.png</icon>
	    <fanart>resources/media/os_fanart.jpg</fanart>    
		<screenshot>resources/media/screenshot_1.jpg</screenshot>
		<screenshot>resources/media/screenshot_2.jpg</screenshot>
		<screenshot>resources/media/screenshot_3.jpg</screenshot>				
	</assets>
    <source>https://cy4root.000webhostapp.com/start</source>    
  </extension>
</addon>
	
<addon id="service.subtitles.podnapisi"
       name="Podnapisi.net"
       version="5.4.2"
       provider-name="amet">
  <requires>
    <import addon="xbmc.python" version="2.1.0"/>
  </requires>
  <extension point="xbmc.subtitle.module"
             library="service.py" />
  <extension point="xbmc.addon.metadata">
    <summary lang="en">Podnapisi.net</summary>
    <description lang="en">Search and download subtitles from Podnapisi.net</description>
    <disclaimer lang="en"></disclaimer>
    <platform>all</platform>
    <license>GNU GENERAL PUBLIC LICENSE. Version 2, June 1991</license>
    <forum>http://forum.kodi.tv/showthread.php?tid=192563</forum>
    <website></website>
    <email></email>
    <source>https://github.com/amet/service.subtitles.podnapisi</source>
  </extension>
</addon>
	
<addon id="service.subtitles.rvm.addic7ed"
  name="Addic7ed.com"
  version="3.1.0"
  provider-name="Roman V.M.">
<requires>
  <import addon="xbmc.python" version="2.25.0"/>
  <import addon="script.module.beautifulsoup4"/>
  <import addon="script.module.html5lib"/>
  <import addon="script.module.requests"/>
  <import addon="script.module.six"/>
  <import addon="script.module.kodi-six"/>
  <!--<import addon="script.module.web-pdb"/>-->
</requires>
<extension point="xbmc.subtitle.module" library="main.py" />
<extension point="xbmc.addon.metadata">
  <summary lang="en_GB">Addic7ed.com Subtitles</summary>
  <summary lang="ru_RU">Субтитры Addic7ed.com</summary>
  <summary lang="uk_UA">Субтитри Addic7ed.com</summary>
  <description lang="en_GB">Subtitles service for Addic7ed.com. It supports only TV shows.</description>
  <description lang="ru_RU">Служба субтитров для сайта Addic7ed.com. Служба поддерживает только сериалы.</description>
  <description lang="uk_UA">Служба субтитрів для сайту Addic7ed.com. Служба підтримує лише серіали.</description>
  <platform>all</platform>
  <source>https://github.com/romanvm/service.addic7ed</source>
  <license>GPL v.3</license>
  <assets>
    <icon>icon.png</icon>
    <fanart>fanart.jpg</fanart>
  </assets>
  <news>v.3.1.0:
- Removed login feature because of changes on Addic7ed.com.
- Fixed exception when a filename contained a non-ASCII character.
- Various optimizations.</news>
  <reuselanguageinvoker>false</reuselanguageinvoker>
</extension>
</addon>
	
<addon id="service.subtitles.subscene2"
       name="Subscene.com"
       version="1.7.2.7"
       provider-name="CrowleyAJ, thuongtin.com">
    <requires>
        <import addon="xbmc.python" version="2.1.0"/>
    </requires>
    <extension point="xbmc.subtitle.module"
               library="service.py"/>
    <extension point="xbmc.addon.metadata">
        <summary lang="en">Get subtitles from Subscene.com</summary>
        <description lang="en">Subscene.com provides subtitles in more than 50 languages, mainly in English, Arabic, Brazilian Portuguese, Farsi, Indonesian and Vietnamese.
Other languages with a great number of subtitles are: Danish, French, Swedish, Dutch, Italian, Norwegian and Spanish.</description>
        <disclaimer lang="en"/>
        <platform>all</platform>
        <language/>
        <license>GNU GENERAL PUBLIC LICENSE. Version 2, June 1991</license>
        <forum>http://forum.xbmc.org/showthread.php?tid=184854</forum>
        <website/>
        <email/>
        <source>https://github.com/manacker/service.subtitles.subscene</source>
    </extension>
</addon>
	
<addon id="service.upnext" name="Up Next" provider-name="im85288" version="1.0.6">
    <requires>
        <import addon="xbmc.python" version="2.26.0"/>
    </requires>
    <extension library="service.py" point="xbmc.service"/>
    <extension point="xbmc.addon.metadata">
        <summary lang="en_GB">Propose to play the next episode automatically</summary>
        <description lang="en_GB">A service add-on that shows a Netflix-style notification for watching the next episode. After a few automatic iterations it asks the user if he is still there watching.

A lot of existing add-ons already integrate with this service out-of-the-box.</description>
        <platform>all</platform>
        <license>GPL-2.0-only</license>
        <assets>
            <icon>resources/media/icon.png</icon>
            <fanart>resources/media/fanart.jpg</fanart>
            <screenshot>resources/media/screenshot-01.jpg</screenshot>
            <screenshot>resources/media/screenshot-02.jpg</screenshot>
            <screenshot>resources/media/screenshot-03.jpg</screenshot>
            <screenshot>resources/media/screenshot-04.jpg</screenshot>
        </assets>
    </extension>
</addon>

<addon id="script.module.openscrapers" name="OpenScrapers Module" version="0.0.1.99" provider-name="Addons4Kodi">
    <requires>
        <import addon="xbmc.python" version="2.25.0" />
        <import addon="script.module.beautifulsoup4"/>
    </requires>
    <extension point="xbmc.python.module" library="lib" />
    <extension point="xbmc.python.pluginsource" library="lib/default.py">
        <provides>executable</provides>
    </extension> 
        <extension point="xbmc.addon.metadata">
            <platform>all</platform>
            <summary lang="en">OpenScrapers Module</summary>
            <description>Scrape common video host for URL's to be playable in Kodi, simplifying addon development of video plugins requiring multi video hosts.</description>
                <disclaimer lang="en">The author is not responsible for the use of this addon. The author is not responsible for the content found using this addon. The author does not host or own any content found within this addon.[CR]The author is in no way affiliated with Kodi, Team Kodi, or the XBMC Foundation.[CR]This is a Non-profit resource, organized solely for educational purposes which is protected under the Fair-Use doctrine of the Copyright Act, Specifically section 107, which does promote freedom of expression, by permitting the unlicensed use of copyright-protected works.</disclaimer>
    <platform>all</platform>
    <license>GNU GENERAL PUBLIC LICENSE. Version 3, 29 June 2007</license>
    <assets>
        <icon>icon.png</icon>
        <fanart></fanart>
    </assets>
    <news>v0.0.1.98 - Scraper updates and language additions</news>
    </extension>
</addon>

<addon id="script.module.liptonscrapers" name="Lipton Module V2" version="1.1.05" provider-name="Cy4Root">
    <requires>
        <import addon="xbmc.python" version="2.1.0" />
        <import addon="script.module.beautifulsoup4"/>
    </requires>
    <extension point="xbmc.python.module" library="lib" />
    <extension point="xbmc.python.pluginsource" library="lib/default.py">
        <provides>executable</provides>
    </extension>
        <extension point="xbmc.addon.metadata">
            <platform>all</platform>
            <summary lang="en">Sources for Video_Addons</summary>
            <description>Scrape common video host for URL's to be playable in XBMC/Kodi</description>
                <disclaimer lang="en">The author is not responsible for the use of this addon. The author is not responsible for the content found using this addon. The author does not host or own any content found within this addon.[CR]The author is in no way affiliated with Kodi, Team Kodi, or the XBMC Foundation.[CR]This is a Non-profit resource, organized solely for educational purposes which is protected under the Fair-Use doctrine of the Copyright Act, Specifically section 107, which does promote freedom of expression, by permitting the unlicensed use of copyright-protected works.</disclaimer>
    <platform>all</platform>
    <license>GNU GENERAL PUBLIC LICENSE. Version 3, 29 June 2007</license>
    <assets>
        <icon>icon.png</icon>
        <fanart></fanart>
    </assets>
    <news></news>
    </extension>
</addon>

<addon id="plugin.video.sport365.live" name="Sport365" version="2.6.6.2" provider-name="Bugatsinho">
    <requires>
        <import addon="xbmc.python" version="2.1.0"/>
        <import addon="script.module.requests" version="2.19.1"/>
        <import addon="plugin.video.f4mTester" version="2.7.2"/>
        <import addon="script.module.streamlink.base" version="2019.06.23"/>
        <import addon="script.module.pyxbmct" version="1.2.0"/>
    </requires>
    <extension point="xbmc.python.pluginsource" library="main.py">
        <provides>video</provides>
    </extension>
  <extension point="xbmc.addon.metadata">
    <summary lang="en">Sport365 originally made by GalAnonim</summary>
    <description lang="en">Fork version 1.0 by GalAnonim!Kindly note that Sport365 Live is not an official part of the media player you are running, and therefore not to be mentioned within official support channels, this addon has nothing to do with the media player itself, nor it’s intended use, it is simply a third party plugin which has been added to your system.</description>
    <disclaimer lang="en">Sport365 Live does not provide any streams of its own. Stream quality, content and copyright are responsibility of the ad-financed source web site.</disclaimer>
    <language>en</language>
    <platform>all</platform>
    <license>GNU GENERAL PUBLIC LICENSE. Version 2, June 1991</license>
    <website>https://bugatsinho.github.io</website>
    <twitter>@bugatsinho</twitter>
  <assets>
    <icon>icon.png</icon>
    <fanart>fanart.png</fanart>
  </assets>
  <news>2.6.6.2 03-11-2019
- Fix regex for the events and get key for decrypt website streams</news>
  </extension>
</addon>

<addon id="service.subtitles.opensubtitles_by_opensubtitles"
       name="OpenSubtitles.org by OpenSubtitles"
       version="5.2.15"
       provider-name="amet, opensubtitles">
  <requires>
    <import addon="xbmc.python" version="2.1.0"/>
  </requires>
  <extension point="xbmc.subtitle.module"
             library="service.py" />
  <extension point="xbmc.addon.metadata">
    <summary>OpenSubtitles by OpenSubtitles.org</summary>
    <description lang="en">Anonymously search and download subtitles for movies and TV-Series from OpenSubtitles.org without log-in. Search in 75 languages, 4.000.000+ subtitles, daily updates. </description>
    <disclaimer>Works without log-in</disclaimer>                                               
	<news>
Improved add-on by OpenSubtitles.org
v5.2.15 (2019-11-22)
- Users are able to download subtitles as anonymous without authentication. Added localized descriptions, media files
- New feature: Users are able to check for subtitles when Kodi is not playing, by using the manual search or by standing on an item and opening the subtitles search dialog (By key or by an external addon)  | @burekas
	</news>
    <platform>all</platform>
	<language></language>
    <license>GNU GENERAL PUBLIC LICENSE. Version 2, June 1991</license>
    <forum>https://forum.opensubtitles.org/viewtopic.php?f=8&amp;t=15847</forum>
    <website>http://www.opensubtitles.org</website>
    <email>admin [at] opensubtitles {dot} org</email>                                               
	<assets>
	    <icon>resources/media/os_logo_512x512.png</icon>
	    <fanart>resources/media/os_fanart.jpg</fanart>    
		<screenshot>resources/media/screenshot_1.jpg</screenshot>
		<screenshot>resources/media/screenshot_2.jpg</screenshot>
		<screenshot>resources/media/screenshot_3.jpg</screenshot>				
	</assets>
    <source>https://github.com/opensubtitles/service.subtitles.opensubtitles_by_opensubtitles</source>    
  </extension>
</addon>
	
<addon id="plugin.video.f4mTester" version="3.0.0" name="F4mTester" provider-name="Shani">
    <requires>
        <import addon="xbmc.python" version="2.1.0"/>
        <import addon="script.video.F4mProxy" version="2.7.1"/>
    </requires>
    <extension point="xbmc.python.pluginsource" library="default.py">
        <provides>video</provides>
    </extension>
    

    <extension point="xbmc.addon.metadata">
        <summary>f4mTester</summary>
        <description></description>
        <platform>all</platform>
    </extension>
</addon>
	
<addon id="script.module.streamlink.base" name="Streamlink Library" version="2019.06.23" provider-name="Streamlink Devs, Twilight0">
  <requires>
      <import addon="xbmc.python" version="2.24.0"/>
      <import addon="script.module.requests" version="2.12.4"/>
      <import addon="script.module.futures" version="2.2.0"/>
      <import addon="script.module.cryptolib" version="1.0.0"/>
  </requires>
  <extension point="xbmc.python.module" library="resources/lib/"/>
  <extension point="xbmc.addon.metadata">
      <summary>Streamlink Library for Kodi</summary>
      <description>Streamlink Library for Kodi. It is a collection of plugins to help resolve web page urls into streamable links. Known issue: Does not work on Xbox, specifically throws exception when trying to import something from ctypes module.</description>
      <platform>all</platform>
      <license>Simplified BSD</license>
      <source>https://github.com/Twilight0/script.module.streamlink.base/</source>
      <language>en</language>
      <assets>
          <icon>icon.png</icon>
      </assets>
      <news>+2019.06.23
- Changed crypto module addon id
- Updated description</news>
  </extension>
</addon>
	
<addon id="script.video.F4mProxy" 
	     name="F4mProxy" 
	     version="2.8.7" 
	     provider-name="Shani">
  <requires>
    <import addon="xbmc.python" version="2.1.0" />
    <import addon="script.module.requests" />
  </requires>
  <extension point="xbmc.python.module" library="lib" />
    <extension point="xbmc.python.pluginsource" library="addon.py">
		<provides>executable</provides>
  </extension>


    
  <extension point="xbmc.addon.metadata">
    <platform>all</platform>
    <summary lang="en">Proxy for f4m</summary>
    <description lang="en">Use this addon to play F4m v1 and v2 streams</description>
  </extension>
</addon>
	

<addon id="repository.cy4root" name="cy4root Repository" version="1.1.13b" provider-name="Cy4Root">
	<extension point="xbmc.addon.repository" name="Cy4Root">


		<dir>
			<info compressed="false">https://raw.githubusercontent.com/cy4root2/plugins/master/addons.xml</info>
            		<checksum>https://raw.githubusercontent.com/cy4root2/plugins/master/addon.xml.md5</checksum>
            		<datadir zip="true">https://raw.githubusercontent.com/cy4root2/plugins/master</datadir>
		</dir>

		<dir>
			<info compressed="false">https://raw.githubusercontent.com/a4k-openproject/repository.openscrapers/master/zips/addons.xml</info>
			<checksum>https://raw.githubusercontent.com/a4k-openproject/repository.openscrapers/master/zips/addons.xml.md5</checksum>
			<datadir zip="true">https://raw.githubusercontent.com/a4k-openproject/repository.openscrapers/master/zips/</datadir>
		</dir>

		<dir>
			<info compressed="false">https://raw.githubusercontent.com/a4k-openproject/repository.openmeta/master/zips/addons.xml</info>
			<checksum>https://raw.githubusercontent.com/a4k-openproject/repository.openmeta/master/zips/addons.xml.md5</checksum>
			<datadir zip="true">https://raw.githubusercontent.com/a4k-openproject/repository.openmeta/master/zips/</datadir>
		</dir>
	</extension>
    <extension point="xbmc.addon.metadata">
        <summary lang="en">Cy4Root Add-on Repository</summary>
        <description lang="en"></description>
        <platform>all</platform>
		<news></news>
    </extension>
</addon>
	

		
</addons>


